[
  {
    "id": 0,
    "location": {
      "backgroundImage": "http://placehold.it/1920x1080&text=apartment",
      "title": "Apartment"
    },
    "choices": [
      {
        "text": "Wait here.",
        "href": 0
      }, {
        "text": "Gas station.",
        "href": 1
      }, {
        "text": "Brewery.",
        "href": 3
      }, {
	"text": "Drink water.",
	"href": 0,
	"local": {
	  "unset": ["bottleOfWater"],
	  "requires": ["bottleOfWater"]
	}
      }, {
	"text": "Fill up bottle of water",
	"href": 0,
	"local": {
	  "set": ["bottleOfWater"]
	}
      }
    ]
  },
  {
    "id": 1,
    "location": {
      "backgroundImage": "http://placehold.it/1920x1080&text=gas-station",
      "title": "Gas station"
    },
    "choices": [
      {
        "text": "Brewery",
        "href": 3
      }, {
        "text": "Lockup",
        "href": 2
      }
    ]
  }, {
    "id": 2,
    "location": {
      "backgroundImage": "http://placehold.it/1920x1080&text=lockup",
      "title": "Lockup"
    },
    "choices": [
      {
        "text": "Apartment",
        "href": 0
      }, {
        "text": "Gas station",
        "href": 1
      }, {
        "text": "Wait here.",
        "href": 2
      }
    ]
  }, {
    "id": 3,
    "location": {
      "backgroundImage": "http://placehold.it/1920x1080&text=brewery",
      "title": "Brewery"
    },
    "choices": [
      {
        "text": "Drink beer.",
        "href": 3
      }, {
        "text": "Restart game.",
        "href": 0
      }
    ]
  }
]
